lisa.py
pytest_lisa-0.1.0.dist-info/entry_points.txt
pytest_lisa-0.1.0.dist-info/WHEEL
pytest_lisa-0.1.0.dist-info/METADATA
pytest_lisa-0.1.0.dist-info/RECORD
